setup.py
WireCheckingTool/__init__.py
WireCheckingTool.egg-info/PKG-INFO
WireCheckingTool.egg-info/SOURCES.txt
WireCheckingTool.egg-info/dependency_links.txt
WireCheckingTool.egg-info/not-zip-safe
WireCheckingTool.egg-info/top_level.txt