Metadata-Version: 1.0
Name: WireCheckingTool
Version: 1.0.0
Summary: This tool is used for checking wires with Raspberry Pi
Home-page: UNKNOWN
Author: Acronics Systems Inc.
Author-email: huy.l.ho@acronicssystems.com
License: Copyright (c) 2017 Acronics. All Rights Reserved
Platform: UNKNOWN
